protonx/__init__.py
protonx/_http.py
protonx/client.py
protonx/embeddings.py
protonx/errors.py
protonx/evaluator.py
protonx/model_list.json
protonx/normalizer.py
protonx/ocr.py
protonx/offline_normalizer.py
protonx/table_detector.py
protonx/version.py
protonx/utils/__init__.py
protonx/utils/import_utils.py
protonx-0.1.8.dist-info/licenses/LICENSE
protonx-0.1.8.dist-info/METADATA
protonx-0.1.8.dist-info/WHEEL
protonx-0.1.8.dist-info/top_level.txt
protonx-0.1.8.dist-info/RECORD
