Metadata-Version: 2.4
Name: protonx
Version: 0.1.8
Summary: ProtonX Python SDK for embeddings and AI APIs
Author-email: ProtonX Engineering <protonxai@gmail.com>
License: MIT
Project-URL: Homepage, https://github.com/protonx-engineering/protonx-python
Project-URL: Issues, https://github.com/protonx-engineering/protonx-python/issues
Requires-Python: >=3.8
License-File: LICENSE
Requires-Dist: requests>=2.31.0
Requires-Dist: transformers>=4.30.0
Requires-Dist: pillow
Provides-Extra: torch
Requires-Dist: torch>=1.12.0; extra == "torch"
Requires-Dist: torchvision>=0.13.0; extra == "torch"
Dynamic: license-file
